quine_mccluskey_tomas789/qm.py
quine_mccluskey_tomas789/__init__.py
quine_mccluskey_tomas789/_version.py
quine_mccluskey_tomas789/_quine_mccluskey_tomas789.cpython-310-i386-linux-gnu.so
quine_mccluskey_tomas789/_quine_mccluskey_tomas789.pyi
quine_mccluskey_tomas789-0.2.5.dist-info/top_level.txt
quine_mccluskey_tomas789-0.2.5.dist-info/METADATA
quine_mccluskey_tomas789-0.2.5.dist-info/LICENSE
quine_mccluskey_tomas789-0.2.5.dist-info/RECORD
quine_mccluskey_tomas789-0.2.5.dist-info/WHEEL
